Metadata-Version: 2.4
Name: brozzler
Version: 1.8.1
Summary: Distributed web crawling with browsers
Home-page: https://github.com/internetarchive/brozzler
Author: Noah Levitt
Author-email: Noah Levitt <nlevitt@archive.org>
Maintainer-email: Vangelis Banos <vangelis@archive.org>, Adam Miller <adam@archive.org>, Barbara Miller <barbara@archive.org>, Alex Dempsey <avdempsey@archive.org>, Misty De Méo <misty@archive.org>
License-Expression: Apache-2.0
Project-URL: Homepage, https://github.com/internetarchive/brozzler
Project-URL: Issues, https://github.com/internetarchive/brozzler/issues
Classifier: Development Status :: 5 - Production/Stable
Classifier: Programming Language :: Python :: 3
Classifier: Programming Language :: Python :: 3.9
Classifier: Operating System :: OS Independent
Classifier: Environment :: Console
Classifier: Topic :: Internet :: WWW/HTTP
Classifier: Topic :: System :: Archiving
Requires-Python: >=3.10
Requires-Dist: PyYAML>=5.1
Requires-Dist: reppy==0.3.4
Requires-Dist: requests>=2.21
Requires-Dist: websocket-client==1.8.0
Requires-Dist: pillow>=5.2.0
Requires-Dist: urlcanon>=0.1.dev23
Requires-Dist: cerberus>=1.0.1
Requires-Dist: jinja2>=2.10
Requires-Dist: cryptography>=2.3
Requires-Dist: python-magic>=0.4.15
Requires-Dist: prometheus-client>=0.20.0
Requires-Dist: structlog>=25.1.0
Provides-Extra: yt-dlp
Requires-Dist: yt-dlp[curl-cffi,default]>=2024.7.25; extra == "yt-dlp"
Provides-Extra: dashboard
Requires-Dist: flask>=1.0; extra == "dashboard"
Requires-Dist: gunicorn>=19.8.1; extra == "dashboard"
Provides-Extra: warcprox
Requires-Dist: warcprox>=2.4.31; extra == "warcprox"
Provides-Extra: rethinkdb
Requires-Dist: rethinkdb==2.4.9; extra == "rethinkdb"
Requires-Dist: doublethink==0.4.9; extra == "rethinkdb"
Requires-Dist: setuptools>=75.8.0; python_version >= "3.12" and extra == "rethinkdb"
Dynamic: author
Dynamic: home-page
